nemreader/__init__.py
nemreader/__main__.py
nemreader/cli.py
nemreader/nem_objects.py
nemreader/nem_reader.py
nemreader/output_db.py
nemreader/outputs.py
nemreader/py.typed
nemreader/split_days.py
nemreader/version.py
nemreader-0.9.2.dist-info/entry_points.txt
nemreader-0.9.2.dist-info/LICENSE
nemreader-0.9.2.dist-info/WHEEL
nemreader-0.9.2.dist-info/METADATA
nemreader-0.9.2.dist-info/RECORD
