Metadata-Version: 2.1
Name: nemreader
Version: 0.9.2
Summary: nemreader
Keywords: energy,NEM12,NEM13
Author-email: Alex Guinman <alex@guinman.id.au>
Requires-Python: >=3.10
Classifier: License :: OSI Approved :: MIT License
Classifier: Programming Language :: Python :: 3
Classifier: Programming Language :: Python :: 3.12
Classifier: Programming Language :: Python :: 3.11
Classifier: Programming Language :: Python :: 3.10
Classifier: Operating System :: OS Independent
Requires-Dist: pandas
Requires-Dist: sqlite_utils
Requires-Dist: typer
Requires-Dist: ruff ; extra == "test"
Requires-Dist: pytest >=2.7.3 ; extra == "test"
Requires-Dist: pytest-cov ; extra == "test"
Requires-Dist: mypy ; extra == "test"
Project-URL: Documentation, https://nem-reader.readthedocs.io/en/latest/
Project-URL: Source, https://github.com/aguinane/nem-reader/
Provides-Extra: test
